README.md
setup.cfg
setup.py
johnbucmoore_package/Binomialdistribution.py
johnbucmoore_package/Gaussiandistribution.py
johnbucmoore_package/Generaldistribution.py
johnbucmoore_package/__init__.py
johnbucmoore_package.egg-info/PKG-INFO
johnbucmoore_package.egg-info/SOURCES.txt
johnbucmoore_package.egg-info/dependency_links.txt
johnbucmoore_package.egg-info/not-zip-safe
johnbucmoore_package.egg-info/top_level.txt