Metadata-Version: 1.0
Name: johnbucmoore-package
Version: 0.1
Summary: Distributions: Gaussian & Binomial
Home-page: UNKNOWN
Author: JohnBucMoore
Author-email: myemail@something.com
License: UNKNOWN
Platform: UNKNOWN
